spacy_streamlit/__init__.py
spacy_streamlit/util.py
spacy_streamlit/visualizer.py
spacy_streamlit-1.0.6.dist-info/LICENSE
spacy_streamlit-1.0.6.dist-info/METADATA
spacy_streamlit-1.0.6.dist-info/WHEEL
spacy_streamlit-1.0.6.dist-info/top_level.txt
spacy_streamlit-1.0.6.dist-info/zip-safe
spacy_streamlit-1.0.6.dist-info/RECORD
