Metadata-Version: 2.1
Name: spacy_streamlit
Version: 1.0.6
Summary: Visualize spaCy with streamlit
Home-page: https://github.com/explosion/spacy-streamlit
Author: Explosion
Author-email: contact@explosion.ai
License: MIT
Requires-Python: >=3.6
License-File: LICENSE
